cfgmgr/__init__.py
cfgmgr/app_config.cpython-38-x86_64-linux-gnu.so
cfgmgr/client.cpython-38-x86_64-linux-gnu.so
cfgmgr/config_manager.cpython-38-x86_64-linux-gnu.so
cfgmgr/exc.py
cfgmgr/publisher.cpython-38-x86_64-linux-gnu.so
cfgmgr/server.cpython-38-x86_64-linux-gnu.so
cfgmgr/subscriber.cpython-38-x86_64-linux-gnu.so
cfgmgr/util.cpython-38-x86_64-linux-gnu.so
eii_configmanager-3.0.dist-info/METADATA
eii_configmanager-3.0.dist-info/WHEEL
eii_configmanager-3.0.dist-info/top_level.txt
eii_configmanager-3.0.dist-info/RECORD
