Metadata-Version: 2.1
Name: eii-configmanager
Version: 3.0
Summary: EII ConfigMgr Python wrapper
Home-page: UNKNOWN
License: UNKNOWN
Keywords: eii configmgr
Platform: UNKNOWN
